MANIFEST.in
README.rst
setup.py
participationgraphs/__init__.py
participationgraphs/models.py
participationgraphs.egg-info/PKG-INFO
participationgraphs.egg-info/SOURCES.txt
participationgraphs.egg-info/dependency_links.txt
participationgraphs.egg-info/top_level.txt
participationgraphs/templatetags/__init__.py
participationgraphs/templatetags/githubgraphs.py
participationgraphs/utils/__init__.py
participationgraphs/utils/github.py