Metadata-Version: 1.0
Name: participationgraphs
Version: 0.1.1
Summary: Django app with a template tag to allow you to include sparklines of the 52-week commit history for a project on Github
Home-page: http://github.com/flother/participationgraphs
Author: Matt Riggott
Author-email: UNKNOWN
License: GPL
Platform: UNKNOWN
Classifier: Development Status :: 4 - Beta
Classifier: Environment :: Web Environment
Classifier: Framework :: Django
Classifier: Intended Audience :: Developers
Classifier: License :: OSI Approved :: GNU General Public License (GPL)
Classifier: Operating System :: OS Independent
Classifier: Programming Language :: Python
Classifier: Topic :: Software Development :: Libraries :: Python Modules
